hsi_moss/__init__.py
hsi_moss/hsi_prepare.py
hsi_moss/spectral_envi.py
hsi_moss/spectral_tiffs.py
hsi_moss-0.0.4.dist-info/METADATA
hsi_moss-0.0.4.dist-info/WHEEL
hsi_moss-0.0.4.dist-info/licenses/LICENSE
hsi_moss-0.0.4.dist-info/RECORD
